textflavour/__init__.py
textflavour/wo.py
textflavour-0.0.2.dist-info/LICENSE
textflavour-0.0.2.dist-info/METADATA
textflavour-0.0.2.dist-info/WHEEL
textflavour-0.0.2.dist-info/top_level.txt
textflavour-0.0.2.dist-info/RECORD
