Metadata-Version: 2.1
Name: textflavour
Version: 0.0.2
Summary: A package for making text look better
Home-page: https://github.com/whyisthesheep/textflavour
Author: whyisthesheep
Project-URL: Bug Tracker, https://github.com/whyisthesheep/textflavour/issues
Classifier: Programming Language :: Python :: 3
Classifier: License :: OSI Approved :: MIT License
Classifier: Operating System :: OS Independent
Requires-Python: >=3.6
License-File: LICENSE
